repotracer/__init__.py
repotracer/commands/__init__.py
repotracer/commands/add.py
repotracer/commands/install_repos.py
repotracer/commands/run.py
repotracer/lib/__init__.py
repotracer/lib/config.py
repotracer/lib/git.py
repotracer/lib/matchers.py
repotracer/lib/measurement.py
repotracer/lib/measurement_fns.py
repotracer/lib/plotter.py
repotracer/lib/stat.py
repotracer/lib/storage.py
repotracer/main.py
repotracer-0.4.3.dist-info/LICENSE.md
repotracer-0.4.3.dist-info/METADATA
repotracer-0.4.3.dist-info/WHEEL
repotracer-0.4.3.dist-info/entry_points.txt
repotracer-0.4.3.dist-info/RECORD
