Metadata-Version: 2.1
Name: repotracer
Version: 0.4.3
Summary: A tool to collect statistics about a git repository over time
Author: Amedee d'Aboville
Author-email: amedee.daboville@gmail.com
Requires-Python: >=3.11,<4.0
Classifier: Programming Language :: Python :: 3
Classifier: Programming Language :: Python :: 3.11
Requires-Dist: dacite (>=1.8.1,<2.0.0)
Requires-Dist: json5 (>=0.9.14,<0.10.0)
Requires-Dist: matplotlib (>=3.7.2,<4.0.0)
Requires-Dist: pandas (>=1.5.3,<2.0.0)
Requires-Dist: pydantic (>=2.1.1,<3.0.0)
Requires-Dist: pytest (>=7.4.3,<8.0.0)
Requires-Dist: pytest-cov (>=4.1.0,<5.0.0)
Requires-Dist: pytest-mock (>=3.12.0,<4.0.0)
Requires-Dist: questionary (>=2.0.0,<3.0.0)
Requires-Dist: s3fs (>=2023.6.0,<2024.0.0)
Requires-Dist: seaborn (>=0.12.2,<0.13.0)
Requires-Dist: sh (>=2.0.4,<3.0.0)
Requires-Dist: tqdm (>=4.64.1,<5.0.0)
Requires-Dist: typer[all] (>=0.9.0,<0.10.0)
